README.md
setup.cfg
setup.py
ipfind/__init__.py
ipfind/ipfind.py
ipfind.egg-info/PKG-INFO
ipfind.egg-info/SOURCES.txt
ipfind.egg-info/dependency_links.txt
ipfind.egg-info/entry_points.txt
ipfind.egg-info/requires.txt
ipfind.egg-info/top_level.txt