Metadata-Version: 1.1
Name: ipfind
Version: 0.4
Summary: simple tools by MrY86 and Mr.K3R3H
Home-page: https://github.com/MrY86
Author: MrY86
Author-email: www.mryama@gmail.com
License: UNKNOWN
Download-URL: https://github.com/MrY86
Keywords: dev3l,archetype,pypi,package
Platform: UNKNOWN
Classifier: Environment :: Console
Classifier: Intended Audience :: Developers
Classifier: License :: OSI Approved :: MIT License
Classifier: Operating System :: OS Independent
Classifier: Programming Language :: Python
Classifier: Programming Language :: Python :: 2
Classifier: Programming Language :: Python :: 3
Classifier: Topic :: Software Development :: Libraries :: Python Modules
